powernad/__init__.py
powernad/API/Ad.py
powernad/API/AdExtension.py
powernad/API/AdGroup.py
powernad/API/AdKeyword.py
powernad/API/Bizmoney.py
powernad/API/BusinessChannel.py
powernad/API/Campaign.py
powernad/API/Estimate.py
powernad/API/IpExclusion.py
powernad/API/Label.py
powernad/API/ManagedCustomerLink.py
powernad/API/MasterReport.py
powernad/API/RelKwdStat.py
powernad/API/Stat.py
powernad/API/StatReport.py
powernad/API/Target.py
powernad/API/__init__.py
powernad/Common/CommonFunctions.py
powernad/Common/__init__.py
powernad/Connector/__init__.py
powernad/Connector/restapi.py
powernad/Object/__init__.py
powernad/Object/Ad/AdObject.py
powernad/Object/Ad/__init__.py
powernad/Object/Ad/RequestObject/CreateAdObject.py
powernad/Object/Ad/RequestObject/UpdateAdObject.py
powernad/Object/Ad/RequestObject/__init__.py
powernad/Object/Ad/sub/AdFieldObject.py
powernad/Object/Ad/sub/__init__.py
powernad/Object/AdExtension/AdExtensionObject.py
powernad/Object/AdExtension/__init__.py
powernad/Object/AdExtension/RequestObject/CreateAdExtensionObject.py
powernad/Object/AdExtension/RequestObject/UpdateAdExtensionObject.py
powernad/Object/AdExtension/RequestObject/__init__.py
powernad/Object/AdGroup/AdgroupObject.py
powernad/Object/AdGroup/RestrictedKeyword.py
powernad/Object/AdGroup/__init__.py
powernad/Object/AdGroup/RequestObject/CreateAdgroupObject.py
powernad/Object/AdGroup/RequestObject/RestrictedKeywordsObject.py
powernad/Object/AdGroup/RequestObject/UpdateAdgroupObject.py
powernad/Object/AdGroup/RequestObject/UpdateEntireAdgroupObject.py
powernad/Object/AdGroup/RequestObject/__init__.py
powernad/Object/AdGroup/sub/__init__.py
powernad/Object/AdGroup/sub/adgroupAttrJson.py
powernad/Object/AdGroup/sub/target.py
powernad/Object/AdGroup/sub/targetSummaryObject.py
powernad/Object/AdKeyword/AdKeywordObject.py
powernad/Object/AdKeyword/ManagedKeywordObject.py
powernad/Object/AdKeyword/__init__.py
powernad-0.8.0.dist-info/METADATA
powernad-0.8.0.dist-info/RECORD
powernad-0.8.0.dist-info/WHEEL
powernad-0.8.0.dist-info/top_level.txt
