Metadata-Version: 2.1
Name: powernad
Version: 0.8.0
Summary: Easy to use naver ad to python
Home-page: https://github.com/devkingsejong/python-PowerNad
Author: devkingsejong
Author-email: devkingsejong@gmail.com
License: UNKNOWN
Keywords: Easy to use naver ad to python
Platform: UNKNOWN
Classifier: Development Status :: 2 - Pre-Alpha
Classifier: Topic :: Software Development :: Libraries
Classifier: Programming Language :: Python :: 3
Classifier: Programming Language :: Python :: 3.4
Classifier: Programming Language :: Python :: 3.5
Classifier: Programming Language :: Python :: 3.6
